<?xml version="1.0" encoding="UTF-8"?>
<images><image id="uploads/2cats.jpg"><caption>Coffe cats!</caption><path>uploads/2cats.jpg</path><date>2016-01-02</date></image><image id="uploads/family.jpg"><caption>Cartoon</caption><path>uploads/family.jpg</path><date>2016-01-03</date></image><image id="uploads/mixed.jpg"><caption>Mixed greatness</caption><path>uploads/mixed.jpg</path><date>2016-01-03</date></image><image id="uploads/cat.jpg"><caption>Blip</caption><path>uploads/cat.jpg</path><date>2016-01-04</date></image></images>
